Workbook

Sheet Read me
A1: Supplier Follow-up Agent: impact model
A2: Illustrative. Every input is an assumption until shadow mode measures it. Designed and directed by Rohit Kumar; built with Claude; 11 Oct 2026.
A4: The answer, in the likely case
A5: Value for one customer per year | B5: ='One customer'!C11 -> 1583145.2
A6: Value for each rupee of price | B6: ='One customer'!C15 -> 7.915726
A7: Payback | B7: ='One customer'!C16 -> 1.5159696
A8: Share of the value from credit no longer lost | B8: ='One customer'!C13 -> 0.7579848
A9: Value in the cautious case (below the ₹2 L price) | B9: ='One customer'!B11 -> 177863.01
A10: AI cost per supplier per cycle | B10: ='AI unit economics'!B24 -> 0.493536
A11: AI cost as a share of the price | B11: ='One customer'!C18 -> 0.0017767296
A13: What it means
A14: Avoided loss carries about three quarters of the value, so the loss rate today (hypothesis H4) decides the business case.
A15: With every input at its cautious end at once, the agent is worth about ₹1.8 L a year, less than a ₹2 L price. No single input on its own pulls the likely case below ₹6.8 L.
A16: AI cost is not the constraint: well under 1% of the price even at older model prices.
A17: So the first two weeks of the rollout measure the loss rate before anything is built.
A19: Sheets
A20: Inputs | B20: Every assumption in three scenarios, with the reason and how it gets measured. Edit the blue cells.
A21: One customer | B21: Value per customer per year, price, payback and AI cost.
A22: Sensitivity | B22: Which input moves the value most, one at a time.
A23: Portfolio | B23: Value, revenue and AI cost if a number of customers adopt.
A24: AI unit economics | B24: Tokens per job, list prices and cost per supplier per cycle.
A25: Demo check | B25: The prototype's simulated cycle, with and without the recommended steps.
A26: Inbox ranking | B26: How the inbox orders suppliers, on the demo data.
A28: Colours
A29: Blue = typed input · black = formula · green = taken from another sheet · yellow = the likely case quoted in the document and slides.
A31: Sources
A32: Model prices: Anthropic pricing page, platform.claude.com/docs/en/about-claude/pricing (opened 11 Oct 2026).
A33: Exchange rate: Upstox currency converter, ₹96.64 per US$ on 11 Oct 2026.
A34: Deadline for FY 2025-26 credit: Section 16(4) of the CGST Act, 30 Nov 2026. Reversal after 180 days unpaid: Rule 37. Supplier not filing GSTR-3B: Rule 37A.
A35: Demo figures: the prototype, on fictional data. No customer data was used anywhere in this model.

Sheet Inputs
A1: Inputs
A2: Blue cells are assumptions: change them and every other sheet updates. None of these has been measured yet.
A4: # | B4: Input | C4: Unit | D4: Cautious | E4: Likely | F4: Strong | G4: Why this value, and how it gets measured
A5: 1 | B5: Flagged supplier-side credit per month | C5: ₹ | D5: 1000000 | E5: 2500000 | F5: 5000000 | G5: Assumption for a mid-size buyer with several GSTINs. The demo company has ₹23.4 L flagged across 16 suppliers. Measured from reco results in shadow mode.
A6: 2 | B6: Share of flagged credit lost for good today | C6: % | D6: 0.03 | E6: 0.06 | F6: 0.1 | G6: Hypothesis H4: credit lost when last year's invoices miss the 30 Nov deadline (Section 16(4)) or suppliers never file (Rule 37A). No public data. The first number shadow mode measures; below 3% the case weakens.
A7: 3 | B7: Share lost with the agent | C7: % | D7: 0.02 | E7: 0.02 | F7: 0.01 | G7: Some suppliers never file whatever we do (closed, in distress), so loss does not reach zero.
A8: 4 | B8: Share fixed within one filing cycle today | C8: % | D8: 0.6 | E8: 0.55 | F8: 0.5 | G8: Assumption: manual chasing with promises tracked in spreadsheets. Measured in shadow mode.
A9: 5 | B9: Share fixed within one filing cycle with the agent | C9: % | D9: 0.7 | E9: 0.8 | F9: 0.85 | G9: First message the day the reco job flags, reminders timed before the 11th, broken promises caught on the 12th. Pilot KR1 targets 70%.
A10: 6 | B10: Days sooner for credit that moves into the first cycle | C10: days | D10: 30 | E10: 60 | F10: 75 | G10: A missed cycle costs about a month; credit that slips usually slips two cycles.
A11: 7 | B11: Cost of capital | C11: % a year | D11: 0.1 | E11: 0.12 | F11: 0.14 | G11: Working-capital rate for a mid-size Indian manufacturer (assumption).
A12: 8 | B12: Suppliers followed up per month | C12: count | D12: 40 | E12: 60 | F12: 100 | G12: Assumption. The demo has 16 suppliers open on one day.
A13: 9 | B13: Minutes per supplier per cycle today | C13: minutes | D13: 30 | E13: 40 | F13: 50 | G13: Reading replies, chasing, updating the tracker (assumption; hypothesis H1 asks this in interviews).
A14: 10 | B14: Minutes per supplier per cycle with the agent | C14: minutes | D14: 18 | E14: 12 | F14: 10 | G14: Checking readings and approving drafts. Pilot KR3 targets under 15.
A15: 11 | B15: Loaded cost of one GST team hour | C15: ₹ | D15: 500 | E15: 700 | F15: 900 | G15: Assumption.
A16: 12 | B16: Price per customer per year | C16: ₹ | D16: 200000 | E16: 200000 | F16: 200000 | G16: Placeholder for a paid add-on. Pricing is an open question (per GSTIN, per supplier, or a share of credit recovered).
A17: 13 | B17: Customers adopting (portfolio view) | C17: count | D17: 60 | E17: 150 | F17: 300 | G17: Assumption for illustration, not Masters India data.
B19: Scenarios: Cautious sets every input at the low-value end at once, Strong at the high end. The Sensitivity sheet moves one input at a time.
B20: Yellow = the likely case used in the document and slides. Blue = typed input; black = formula; green = taken from another sheet.

Sheet One customer
A1: Value for one customer, per year
A2: What the agent is worth to one mid-size buyer, and what it costs to run. Every number is a formula on the Inputs sheet.
A4: Line | B4: Cautious | C4: Likely | D4: Strong | E4: How it is calculated
A5: Flagged supplier-side credit per year | B5: =Inputs!$D$5*12 -> 12000000 | C5: =Inputs!$E$5*12 -> 30000000 | D5: =Inputs!$F$5*12 -> 60000000 | E5: Flagged per month × 12
A6: Credit no longer lost for good | B6: =B5*(Inputs!$D$6-Inputs!$D$7) -> 120000 | C6: =C5*(Inputs!$E$6-Inputs!$E$7) -> 1200000 | D6: =D5*(Inputs!$F$6-Inputs!$F$7) -> 5400000 | E6: Flagged × (share lost today − share lost with the agent)
A7: Credit now fixed within the first cycle | B7: =B5*(Inputs!$D$9-Inputs!$D$8) -> 1200000 | C7: =C5*(Inputs!$E$9-Inputs!$E$8) -> 7500000 | D7: =D5*(Inputs!$F$9-Inputs!$F$8) -> 21000000 | E7: Flagged × (share fixed in one cycle with the agent − today)
A8: Value of receiving that credit sooner | B8: =B7*Inputs!$D$11*Inputs!$D$10/365 -> 9863.0137 | C8: =C7*Inputs!$E$11*Inputs!$E$10/365 -> 147945.21 | D8: =D7*Inputs!$F$11*Inputs!$F$10/365 -> 604109.59 | E8: Credit fixed sooner × cost of capital × days sooner ÷ 365
A9: GST team hours saved | B9: =Inputs!$D$12*12*(Inputs!$D$13-Inputs!$D$14)/60 -> 96 | C9: =Inputs!$E$12*12*(Inputs!$E$13-Inputs!$E$14)/60 -> 336 | D9: =Inputs!$F$12*12*(Inputs!$F$13-Inputs!$F$14)/60 -> 800 | E9: Suppliers per month × 12 × minutes saved ÷ 60
A10: Value of time saved | B10: =B9*Inputs!$D$15 -> 48000 | C10: =C9*Inputs!$E$15 -> 235200 | D10: =D9*Inputs!$F$15 -> 720000 | E10: Hours saved × loaded cost of an hour
A11: Total value per customer per year | B11: =B6+B8+B10 -> 177863.01 | C11: =C6+C8+C10 -> 1583145.2 | D11: =D6+D8+D10 -> 6724109.6 | E11: Credit no longer lost + value of getting it sooner + value of time saved
A12: Total value, in lakh | B12: =B11/100000 -> 1.7786301 | C12: =C11/100000 -> 15.831452 | D12: =D11/100000 -> 67.241096 | E12: Total ÷ 1,00,000
A13: Share of the value that comes from avoided loss | B13: =IF(B11=0,0,B6/B11) -> 0.67467652 | C13: =IF(C11=0,0,C6/C11) -> 0.7579848 | D13: =IF(D11=0,0,D6/D11) -> 0.80308031 | E13: Credit no longer lost ÷ total value
A14: Price per customer per year | B14: =Inputs!$D$16 -> 200000 | C14: =Inputs!$E$16 -> 200000 | D14: =Inputs!$F$16 -> 200000 | E14: From Inputs
A15: Value for each rupee of price | B15: =IF(B14=0,0,B11/B14) -> 0.88931507 | C15: =IF(C14=0,0,C11/C14) -> 7.915726 | D15: =IF(D14=0,0,D11/D14) -> 33.620548 | E15: Total value ÷ price
A16: Payback | B16: =IF(B11=0,0,B14/(B11/12)) -> 13.49353 | C16: =IF(C11=0,0,C14/(C11/12)) -> 1.5159696 | D16: =IF(D11=0,0,D14/(D11/12)) -> 0.35692458 | E16: Price ÷ monthly value
A17: AI cost to run, per customer per year | B17: ='AI unit economics'!C26 -> 1539.8323 | C17: ='AI unit economics'!B26 -> 355.34592 | D17: ='AI unit economics'!B26 -> 355.34592 | E17: Cautious uses the high-cost AI case; Likely and Strong use the likely case
A18: AI cost as a share of the price | B18: =IF(B14=0,0,B17/B14) -> 0.0076991616 | C18: =IF(C14=0,0,C17/C14) -> 0.0017767296 | D18: =IF(D14=0,0,D17/D14) -> 0.0017767296 | E18: AI cost ÷ price
A20: Reading it: avoided loss carries most of the value, so the loss rate today (hypothesis H4) decides the case. In the cautious case the agent is worth less than its price.
A21: Credit received sooner is valued only for the time gained (cost of capital), not counted as new money.

Sheet Sensitivity
A1: What moves the value most
A2: Total value per customer per year with one input moved to its cautious or strong value and every other input at likely.
A4: Input moved | B4: Value at cautious | C4: Value at strong | D4: Swing | E4: Cautious → strong value of the input
A5: Flagged supplier-side credit per month | B5: =12*Inputs!$D$5*(Inputs!$E$6-Inputs!$E$7)+12*Inputs!$D$5*(Inputs!$E$9-Inputs!$E$8)*Inputs!$E$11*Inputs!$E$10/365+Inputs!$E$12*12*(Inputs!$E$13-Inputs!$E$14)/60*Inputs!$E$15 -> 774378.08 | C5: =12*Inputs!$F$5*(Inputs!$E$6-Inputs!$E$7)+12*Inputs!$F$5*(Inputs!$E$9-Inputs!$E$8)*Inputs!$E$11*Inputs!$E$10/365+Inputs!$E$12*12*(Inputs!$E$13-Inputs!$E$14)/60*Inputs!$E$15 -> 2931090.4 | D5: =ABS(C5-B5) -> 2156712.3 | E5: =TEXT(Inputs!$D$5,"#,##0")&" → "&TEXT(Inputs!$F$5,"#,##0") -> 1,000,000 → 5,000,000
A6: Share of flagged credit lost for good today | B6: =12*Inputs!$E$5*(Inputs!$D$6-Inputs!$E$7)+12*Inputs!$E$5*(Inputs!$E$9-Inputs!$E$8)*Inputs!$E$11*Inputs!$E$10/365+Inputs!$E$12*12*(Inputs!$E$13-Inputs!$E$14)/60*Inputs!$E$15 -> 683145.21 | C6: =12*Inputs!$E$5*(Inputs!$F$6-Inputs!$E$7)+12*Inputs!$E$5*(Inputs!$E$9-Inputs!$E$8)*Inputs!$E$11*Inputs!$E$10/365+Inputs!$E$12*12*(Inputs!$E$13-Inputs!$E$14)/60*Inputs!$E$15 -> 2783145.2 | D6: =ABS(C6-B6) -> 2100000 | E6: =TEXT(Inputs!$D$6,"0%")&" → "&TEXT(Inputs!$F$6,"0%") -> 3% → 10%
A7: Share lost with the agent | B7: =12*Inputs!$E$5*(Inputs!$E$6-Inputs!$D$7)+12*Inputs!$E$5*(Inputs!$E$9-Inputs!$E$8)*Inputs!$E$11*Inputs!$E$10/365+Inputs!$E$12*12*(Inputs!$E$13-Inputs!$E$14)/60*Inputs!$E$15 -> 1583145.2 | C7: =12*Inputs!$E$5*(Inputs!$E$6-Inputs!$F$7)+12*Inputs!$E$5*(Inputs!$E$9-Inputs!$E$8)*Inputs!$E$11*Inputs!$E$10/365+Inputs!$E$12*12*(Inputs!$E$13-Inputs!$E$14)/60*Inputs!$E$15 -> 1883145.2 | D7: =ABS(C7-B7) -> 300000 | E7: =TEXT(Inputs!$D$7,"0%")&" → "&TEXT(Inputs!$F$7,"0%") -> 2% → 1%
A8: Suppliers followed up per month | B8: =12*Inputs!$E$5*(Inputs!$E$6-Inputs!$E$7)+12*Inputs!$E$5*(Inputs!$E$9-Inputs!$E$8)*Inputs!$E$11*Inputs!$E$10/365+Inputs!$D$12*12*(Inputs!$E$13-Inputs!$E$14)/60*Inputs!$E$15 -> 1504745.2 | C8: =12*Inputs!$E$5*(Inputs!$E$6-Inputs!$E$7)+12*Inputs!$E$5*(Inputs!$E$9-Inputs!$E$8)*Inputs!$E$11*Inputs!$E$10/365+Inputs!$F$12*12*(Inputs!$E$13-Inputs!$E$14)/60*Inputs!$E$15 -> 1739945.2 | D8: =ABS(C8-B8) -> 235200 | E8: =TEXT(Inputs!$D$12,"#,##0")&" → "&TEXT(Inputs!$F$12,"#,##0") -> 40 → 100
A9: Minutes per supplier per cycle today | B9: =12*Inputs!$E$5*(Inputs!$E$6-Inputs!$E$7)+12*Inputs!$E$5*(Inputs!$E$9-Inputs!$E$8)*Inputs!$E$11*Inputs!$E$10/365+Inputs!$E$12*12*(Inputs!$D$13-Inputs!$E$14)/60*Inputs!$E$15 -> 1499145.2 | C9: =12*Inputs!$E$5*(Inputs!$E$6-Inputs!$E$7)+12*Inputs!$E$5*(Inputs!$E$9-Inputs!$E$8)*Inputs!$E$11*Inputs!$E$10/365+Inputs!$E$12*12*(Inputs!$F$13-Inputs!$E$14)/60*Inputs!$E$15 -> 1667145.2 | D9: =ABS(C9-B9) -> 168000 | E9: =TEXT(Inputs!$D$13,"#,##0")&" → "&TEXT(Inputs!$F$13,"#,##0") -> 30 → 50
A10: Loaded cost of one GST team hour | B10: =12*Inputs!$E$5*(Inputs!$E$6-Inputs!$E$7)+12*Inputs!$E$5*(Inputs!$E$9-Inputs!$E$8)*Inputs!$E$11*Inputs!$E$10/365+Inputs!$E$12*12*(Inputs!$E$13-Inputs!$E$14)/60*Inputs!$D$15 -> 1515945.2 | C10: =12*Inputs!$E$5*(Inputs!$E$6-Inputs!$E$7)+12*Inputs!$E$5*(Inputs!$E$9-Inputs!$E$8)*Inputs!$E$11*Inputs!$E$10/365+Inputs!$E$12*12*(Inputs!$E$13-Inputs!$E$14)/60*Inputs!$F$15 -> 1650345.2 | D10: =ABS(C10-B10) -> 134400 | E10: =TEXT(Inputs!$D$15,"#,##0")&" → "&TEXT(Inputs!$F$15,"#,##0") -> 500 → 900
A11: Days sooner for credit that moves into the first cycle | B11: =12*Inputs!$E$5*(Inputs!$E$6-Inputs!$E$7)+12*Inputs!$E$5*(Inputs!$E$9-Inputs!$E$8)*Inputs!$E$11*Inputs!$D$10/365+Inputs!$E$12*12*(Inputs!$E$13-Inputs!$E$14)/60*Inputs!$E$15 -> 1509172.6 | C11: =12*Inputs!$E$5*(Inputs!$E$6-Inputs!$E$7)+12*Inputs!$E$5*(Inputs!$E$9-Inputs!$E$8)*Inputs!$E$11*Inputs!$F$10/365+Inputs!$E$12*12*(Inputs!$E$13-Inputs!$E$14)/60*Inputs!$E$15 -> 1620131.5 | D11: =ABS(C11-B11) -> 110958.9 | E11: =TEXT(Inputs!$D$10,"#,##0")&" → "&TEXT(Inputs!$F$10,"#,##0") -> 30 → 75
A12: Share fixed within one filing cycle with the agent | B12: =12*Inputs!$E$5*(Inputs!$E$6-Inputs!$E$7)+12*Inputs!$E$5*(Inputs!$D$9-Inputs!$E$8)*Inputs!$E$11*Inputs!$E$10/365+Inputs!$E$12*12*(Inputs!$E$13-Inputs!$E$14)/60*Inputs!$E$15 -> 1523967.1 | C12: =12*Inputs!$E$5*(Inputs!$E$6-Inputs!$E$7)+12*Inputs!$E$5*(Inputs!$F$9-Inputs!$E$8)*Inputs!$E$11*Inputs!$E$10/365+Inputs!$E$12*12*(Inputs!$E$13-Inputs!$E$14)/60*Inputs!$E$15 -> 1612734.2 | D12: =ABS(C12-B12) -> 88767.123 | E12: =TEXT(Inputs!$D$9,"0%")&" → "&TEXT(Inputs!$F$9,"0%") -> 70% → 85%
A13: Minutes per supplier per cycle with the agent | B13: =12*Inputs!$E$5*(Inputs!$E$6-Inputs!$E$7)+12*Inputs!$E$5*(Inputs!$E$9-Inputs!$E$8)*Inputs!$E$11*Inputs!$E$10/365+Inputs!$E$12*12*(Inputs!$E$13-Inputs!$D$14)/60*Inputs!$E$15 -> 1532745.2 | C13: =12*Inputs!$E$5*(Inputs!$E$6-Inputs!$E$7)+12*Inputs!$E$5*(Inputs!$E$9-Inputs!$E$8)*Inputs!$E$11*Inputs!$E$10/365+Inputs!$E$12*12*(Inputs!$E$13-Inputs!$F$14)/60*Inputs!$E$15 -> 1599945.2 | D13: =ABS(C13-B13) -> 67200 | E13: =TEXT(Inputs!$D$14,"#,##0")&" → "&TEXT(Inputs!$F$14,"#,##0") -> 18 → 10
A14: Share fixed within one filing cycle today | B14: =12*Inputs!$E$5*(Inputs!$E$6-Inputs!$E$7)+12*Inputs!$E$5*(Inputs!$E$9-Inputs!$D$8)*Inputs!$E$11*Inputs!$E$10/365+Inputs!$E$12*12*(Inputs!$E$13-Inputs!$E$14)/60*Inputs!$E$15 -> 1553556.2 | C14: =12*Inputs!$E$5*(Inputs!$E$6-Inputs!$E$7)+12*Inputs!$E$5*(Inputs!$E$9-Inputs!$F$8)*Inputs!$E$11*Inputs!$E$10/365+Inputs!$E$12*12*(Inputs!$E$13-Inputs!$E$14)/60*Inputs!$E$15 -> 1612734.2 | D14: =ABS(C14-B14) -> 59178.082 | E14: =TEXT(Inputs!$D$8,"0%")&" → "&TEXT(Inputs!$F$8,"0%") -> 60% → 50%
A15: Cost of capital | B15: =12*Inputs!$E$5*(Inputs!$E$6-Inputs!$E$7)+12*Inputs!$E$5*(Inputs!$E$9-Inputs!$E$8)*Inputs!$D$11*Inputs!$E$10/365+Inputs!$E$12*12*(Inputs!$E$13-Inputs!$E$14)/60*Inputs!$E$15 -> 1558487.7 | C15: =12*Inputs!$E$5*(Inputs!$E$6-Inputs!$E$7)+12*Inputs!$E$5*(Inputs!$E$9-Inputs!$E$8)*Inputs!$F$11*Inputs!$E$10/365+Inputs!$E$12*12*(Inputs!$E$13-Inputs!$E$14)/60*Inputs!$E$15 -> 1607802.7 | D15: =ABS(C15-B15) -> 49315.068 | E15: =TEXT(Inputs!$D$11,"0%")&" → "&TEXT(Inputs!$F$11,"0%") -> 10% → 14%
A17: Likely total, for reference | B17: =12*Inputs!$E$5*(Inputs!$E$6-Inputs!$E$7)+12*Inputs!$E$5*(Inputs!$E$9-Inputs!$E$8)*Inputs!$E$11*Inputs!$E$10/365+Inputs!$E$12*12*(Inputs!$E$13-Inputs!$E$14)/60*Inputs!$E$15 -> 1583145.2
A18: Rows are sorted by swing as built; if you change the inputs, re-sort by the Swing column.

Sheet Portfolio
A1: Portfolio view
A2: If a number of customers adopt it: value created for them, revenue, and AI cost. Illustration only; adoption is an assumption.
A4: Line | B4: Cautious | C4: Likely | D4: Strong | E4: How it is calculated
A5: Customers adopting | B5: =Inputs!$D$17 -> 60 | C5: =Inputs!$E$17 -> 150 | D5: =Inputs!$F$17 -> 300 | E5: From Inputs (assumption)
A6: Value created for customers per year | B6: =B5*'One customer'!B11 -> 10671781 | C6: =C5*'One customer'!C11 -> 2.3747178e+08 | D6: =D5*'One customer'!D11 -> 2.0172329e+09 | E6: Customers × value per customer
A7: Revenue per year | B7: =B5*'One customer'!B14 -> 12000000 | C7: =C5*'One customer'!C14 -> 30000000 | D7: =D5*'One customer'!D14 -> 60000000 | E7: Customers × price
A8: Revenue per year, in crore | B8: =B7/10000000 -> 1.2 | C8: =C7/10000000 -> 3 | D8: =D7/10000000 -> 6 | E8: Revenue ÷ 1,00,00,000
A9: AI cost per year | B9: =B5*'One customer'!B17 -> 92389.939 | C9: =C5*'One customer'!C17 -> 53301.888 | D9: =D5*'One customer'!D17 -> 106603.78 | E9: Customers × AI cost per customer
A10: AI cost as a share of revenue | B10: =IF(B7=0,0,B9/B7) -> 0.0076991616 | C10: =IF(C7=0,0,C9/C7) -> 0.0017767296 | D10: =IF(D7=0,0,D9/D7) -> 0.0017767296 | E10: AI cost ÷ revenue
A12: Scenario columns compound: the cautious column has cautious adoption and cautious value per customer.

Sheet AI unit economics
A1: AI unit economics
A2: What the AI costs per reply, per supplier per cycle and per customer per year, at list prices on 11 Oct 2026.
A4: Model | B4: Input (US$ per million tokens) | C4: Output (US$ per million tokens) | D4: Role
A5: Claude Haiku 5.5 | B5: 0.1 | C5: 0.5 | D5: Runs every job (likely case)
A6: Claude Sonnet 5.5 | B6: 2 | C6: 10 | D6: Retry after a failed check (likely case)
A7: Claude Haiku 4.5 | B7: 1 | C7: 5 | D7: Older quick model: the high-cost case
A8: Claude Sonnet 4.5 | B8: 3 | C8: 15 | D8: Retry in the high-cost case
A9: Source: Anthropic pricing page (platform.claude.com/docs/en/about-claude/pricing), opened 11 Oct 2026; Haiku 5.5 price for prompts up to 100,000 tokens.
A11: Rupees per US dollar | B11: 97 | C11: Mid-market rate ₹96.64 on 11 Oct 2026 (Upstox currency converter), rounded up.
A12: Share of calls retried on the larger model | B12: 0.1 | C12: Assumption. No reading failed its checks in the 40-reply blind test, so 1 in 10 is cautious.
A14: Job | B14: Input tokens per call | C14: Output tokens per call | D14: Calls per supplier per cycle | E14: Input tokens per cycle | F14: Output tokens per cycle
A15: Read a reply | B15: 1430 | C15: 270 | D15: 2 | E15: =B15*D15 -> 2860 | F15: =C15*D15 -> 540
A16: Draft a message | B16: 500 | C16: 190 | D16: 3 | E16: =B16*D16 -> 1500 | F16: =C16*D16 -> 570
A17: Summarise the supplier | B17: 1150 | C17: 140 | D17: 3 | E17: =B17*D17 -> 3450 | F17: =C17*D17 -> 420
A18: Answer a question | B18: 1000 | C18: 100 | D18: 1 | E18: =B18*D18 -> 1000 | F18: =C18*D18 -> 100
A19: Total per supplier per cycle | E19: =SUM(E15:E18) -> 8810 | F19: =SUM(F15:F18) -> 1630
A20: Tokens estimated as characters ÷ 3 from the prototype's real prompts and recorded outputs (mixed English and Indian languages). Calls per cycle: first message, reminder and follow-up; two replies; three summary refreshes; one question.
A22: Result | B22: Likely (Haiku 5.5, retries on Sonnet 5.5) | C22: High cost (Haiku 4.5, retries on Sonnet 4.5) | D22: How it is calculated
A23: Cost of reading one reply, no retry (₹) | B23: =(B15*B5+C15*C5)/1000000*$B$11 -> 0.026966 | C23: =(B15*B7+C15*C7)/1000000*$B$11 -> 0.26966 | D23: Tokens × price ÷ 1,000,000 × rupees per dollar
A24: Cost per supplier per cycle (₹) | B24: =((E19*B5+F19*C5)+$B$12*(E19*B6+F19*C6))/1000000*$B$11 -> 0.493536 | C24: =((E19*B7+F19*C7)+$B$12*(E19*B8+F19*C8))/1000000*$B$11 -> 2.138656 | D24: All calls on the quick model, plus the retried share again on the larger model
A25: Suppliers followed up per year (likely) | B25: =Inputs!$E$12*12 -> 720 | C25: =Inputs!$E$12*12 -> 720 | D25: Suppliers per month × 12
A26: AI cost per customer per year (₹) | B26: =B24*B25 -> 355.34592 | C26: =C24*C25 -> 1539.8323 | D26: Cost per supplier-cycle × suppliers per year
A27: AI cost as a share of the price | B27: =B26/Inputs!$E$16 -> 0.0017767296 | C27: =C26/Inputs!$E$16 -> 0.0076991616 | D27: AI cost ÷ price per customer per year

Sheet Demo check
A1: Demo check: the prototype's simulated cycle
A2: Kestrel Auto Components (fictional), 15 Oct to 14 Nov 2026, as the prototype computes it. This sheet does not feed the model.
A4: On 14 Nov 2026 | B4: Recommended steps taken on 15 Oct | C4: Nothing done | D4: Note
A5: Flagged | B5: 2340396 | C5: 2340396 | D5: 29 invoices, 16 suppliers
A6: Recovered (in GSTR-2B) | B6: 2236716 | C6: 642366 | D6: Includes ₹52,200 already in the September GSTR-2B
A7: Lost for good (FY 2025-26, missed 30 Nov) | B7: 0 | C7: 625500 | D7: Nova ₹4,00,500, Vega ₹1,24,200, Rathi ₹1,00,800
A8: Still open | B8: 90000 | C8: 1072530 | D8: With action: GreenLeaf ₹86,400 promised for December; Krishna ₹3,600 broken promise
A9: Removed: duplicate in our own books | B9: 13680 | C9: 0 | D9: ST/2231-B, not real credit
A11: Check: parts add up to flagged | B11: =IF(SUM(B6:B9)=B5,"Yes","No") -> Yes | C11: =IF(SUM(C6:C9)=C5,"Yes","No") -> Yes
A12: Real credit (flagged less the duplicate) | B12: =B5-13680 -> 2326716 | C12: =C5-13680 -> 2326716
A13: Share of real credit recovered | B13: =B6/B12 -> 0.96131887 | C13: =C6/C12 -> 0.27608268
A14: Share of real credit lost for good | B14: =B7/B12 -> 0 | C14: =C7/C12 -> 0.26883384
A16: The demo is built to show the mechanism, not the rate: it puts three FY 2025-26 cases into one month, so its loss without action (about 27%) is far above the 6% the model assumes.
A17: Blue figures are the prototype's outputs, copied as values. Source: the prototype's model (model.js) on fictional data.

Sheet Inbox ranking
A1: How the inbox is ranked
A2: Protect what can't be undone first: last year's credit outranks bigger amounts that can still be claimed later.
A4: Order of the rules
A5: 1. Group: Needs you, then Lost or missing, Promised, Waiting, Seen in IMS, Fixed.
A6: 2. Within a group: suppliers with FY 2025-26 credit first (rule R8), because it cannot be claimed after 30 Nov 2026.
A7: 3. Then, for promised suppliers, the earliest promised date first.
A8: 4. Then the largest credit stuck first.
A10: Rank | B10: Supplier | C10: Status on 15 Oct 2026 | D10: Last year's credit (₹) | E10: Credit stuck (₹) | F10: Why it sits here
A11: 1 | B11: Nova Polymers | C11: Needs you | D11: 400500 | E11: 537300 | F11: Needs a decision; the most FY 2025-26 credit
A12: 2 | B12: Vega Chemicals | C12: Needs you | D12: 124200 | E12: 202500 | F12: Needs a decision; FY 2025-26 credit
A13: 3 | B13: Rathi Alloys | C13: Needs you | D13: 100800 | E13: 158400 | F13: Needs a decision; FY 2025-26 credit
A14: 4 | B14: Patel Steel Traders | C14: Needs you | D14: 0 | E14: 427500 | F14: Needs a decision; largest current-year credit
A15: 5 | B15: Delta Engineering Works | C15: Not contacted | D15: 0 | E15: 226800 | F15: Needs the first message
A16: 6 | B16: GreenLeaf Facility Services | C16: Needs you | D16: 0 | E16: 86400 | F16: Contact has left
A17: 7 | B17: Mehta Castings | C17: Fix in our books | D17: 0 | E17: 59400 | F17: Our entry is wrong
A18: 8 | B18: Jyoti Industrial Gases | C18: Needs you | D18: 0 | E18: 54900 | F18: Angry denial
A19: 9 | B19: Sai Tooling Solutions | C19: Needs you | D19: 0 | E19: 38970 | F19: Duplicate in our books
A20: 10 | B20: Orbit Office Supplies | C20: Not contacted | D20: 0 | E20: 3330 | F20: Needs the first message
A21: 11 | B21: Bharat Fasteners | C21: Needs you | D21: 0 | E21: 2520 | F21: Wants documents
A22: 12 | B22: Kaveri Precision | C22: Promised 16 Oct | D22: 0 | E22: 3060 | F22: Earliest promise
... A26: 16 | B26: Apex Machine Tools | C26: Waiting for supplier | D26: 0 | E26: 333000 | F26: Out of office until 20 Oct
B27: Total | D27: =SUM(D11:D26) -> 625500 | E27: =SUM(E11:E26) -> 2288196
B28: Needs you (first 11 rows) | E28: =SUM(E11:E21) -> 1798020
B29: Order and amounts as the prototype shows them on 15 Oct 2026 (fictional data). Credit stuck excludes ₹52,200 already recovered.
